eins/__about__.py
eins/__init__.py
eins/combination.py
eins/common_types.py
eins/concrete.py
eins/constraint.py
eins/einsop.py
eins/elementwise.py
eins/namespaces.py
eins/parsing.py
eins/program.py
eins/reduction.py
eins/strategy.py
eins/symbolic.py
eins/transformation.py
eins/utils.py
eins-0.1.1.dist-info/METADATA
eins-0.1.1.dist-info/WHEEL
eins-0.1.1.dist-info/licenses/LICENSE.txt
eins-0.1.1.dist-info/RECORD
