Metadata-Version: 2.3
Name: eins
Version: 0.1.1
Summary: One tensor operation is all you need
Project-URL: Documentation, https://github.com/nicholas-miklaucic/eins#readme
Project-URL: Issues, https://github.com/nicholas-miklaucic/eins/issues
Project-URL: Source, https://github.com/nicholas-miklaucic/eins
Author-email: Nicholas Miklaucic <nicholas.miklaucic@gmail.com>
License-Expression: MIT
License-File: LICENSE.txt
Keywords: array manipulation,artificial intelligence,deep learning,einops,machine learning,neural networks,scientific computing,tensor manipulation
Classifier: Development Status :: 4 - Beta
Classifier: Intended Audience :: Developers
Classifier: Intended Audience :: Science/Research
Classifier: License :: OSI Approved :: MIT License
Classifier: Programming Language :: Python :: 3
Classifier: Programming Language :: Python :: 3.8
Classifier: Programming Language :: Python :: 3.9
Classifier: Programming Language :: Python :: 3.10
Classifier: Programming Language :: Python :: 3.11
Classifier: Programming Language :: Python :: 3.12
Classifier: Programming Language :: Python :: Implementation :: CPython
Classifier: Programming Language :: Python :: Implementation :: PyPy
Classifier: Topic :: Scientific/Engineering :: Artificial Intelligence
Classifier: Topic :: Software Development :: Libraries :: Python Modules
Classifier: Typing :: Typed
Requires-Python: >=3.8
Requires-Dist: array-api-compat
Requires-Dist: pyparsing
Requires-Dist: typing-extensions
